high_percentiolimit/high_percentiolimit.py
high_percentiolimit/high_percentiolimit.rego
high_percentiolimit/manifest.toml
high_percentiolimit/test_high_percentiolimit.py
opsbox_efs_checks-0.1.0.dist-info/licenses/LICENCE.txt
opsbox_efs_checks-0.1.0.dist-info/METADATA
opsbox_efs_checks-0.1.0.dist-info/WHEEL
opsbox_efs_checks-0.1.0.dist-info/entry_points.txt
opsbox_efs_checks-0.1.0.dist-info/top_level.txt
opsbox_efs_checks-0.1.0.dist-info/RECORD
