Metadata-Version: 2.4
Name: opsbox-efs-checks
Version: 0.1.0
Summary: Collection of EFS checks for opsbox
License: Mozilla Public License Version 2.0
Requires-Python: ==3.11.*
License-File: LICENCE.txt
Requires-Dist: opsbox-efs-provider>=0.1.0
Requires-Dist: opsbox-rego-handler>=0.2.0
Dynamic: license-file
